LICENSE
NOTICE
README.md
setup.cfg
setup.py
src/NeoCompilerModelLoaders.egg-info/PKG-INFO
src/NeoCompilerModelLoaders.egg-info/SOURCES.txt
src/NeoCompilerModelLoaders.egg-info/dependency_links.txt
src/NeoCompilerModelLoaders.egg-info/requires.txt
src/NeoCompilerModelLoaders.egg-info/top_level.txt
src/neo_loader/__init__.py
src/neo_loader/_base.py
src/neo_loader/abstract_model_loader.py
src/neo_loader/convert_layout_mixin.py
src/neo_loader/darknet_model_loader.py
src/neo_loader/keras_model_loader.py
src/neo_loader/mxnet_model_loader.py
src/neo_loader/onnx_model_loader.py
src/neo_loader/pytorch_model_loader.py
src/neo_loader/sklearn_model_loader.py
src/neo_loader/tensorflow_model_loader.py
src/neo_loader/tflite_model_loader.py
src/neo_loader/xgboost_model_loader.py
src/neo_loader/helpers/__init__.py
src/neo_loader/helpers/abstract_model_helper.py
src/neo_loader/helpers/tf_model_helper.py
src/neo_loader/helpers/tflite_model_helper.py
test/test_darknet_model_loader.py
test/test_keras_model_loader.py
test/test_mxnet_model_loader.py
test/test_onnx_model_loader.py
test/test_pytorch_model_loader.py
test/test_sklearn_model_loader.py
test/test_tensorflow_model_loader.py
test/test_tflite_model_helper.py
test/test_tflite_model_loader.py
test/test_xgboost_model_loader.py