Metadata-Version: 2.1
Name: NeoCompilerModelLoaders
Version: 1.0.1
Summary: Common libraries for converting machine learning models to TVM Relay IR
Home-page: https://github.com/neo-ai/neo-ai-dlr
Author: AWS Neo
Author-email: aws-neo-ai@amazon.com
License: Apache-2.0
Platform: UNKNOWN
Classifier: Development Status :: 5 - Production/Stable
Classifier: Topic :: Utilities
Classifier: License :: OSI Approved :: Apache Software License
Requires-Python: >=3.5
Provides-Extra: test
